README.rst
setup.py
optimoida/__init__.py
optimoida/__main__.py
optimoida/cli.py
optimoida/config.py
optimoida/core.py
optimoida/logging.py
optimoida.egg-info/PKG-INFO
optimoida.egg-info/SOURCES.txt
optimoida.egg-info/dependency_links.txt
optimoida.egg-info/entry_points.txt
optimoida.egg-info/requires.txt
optimoida.egg-info/top_level.txt