Metadata-Version: 1.1
Name: optimoida
Version: 1.0.0b1
Summary: The optimoida is a command line application to optimize image file (jpg, png only) by TinyPNG API
Home-page: https://github.com/alice1017/optimoida
Author: Hayato Tominaga
Author-email: takemehighermore@gmail.com
License: MIT License
Platform: UNKNOWN
Classifier: Development Status :: 4 - Beta
Classifier: License :: OSI Approved :: MIT License
Classifier: Programming Language :: Python :: 2.7
Classifier: Programming Language :: Python :: 2 :: Only
Classifier: Topic :: Utilities
